odoo/addons/l10n_br_mdfe/README.rst
odoo/addons/l10n_br_mdfe/__init__.py
odoo/addons/l10n_br_mdfe/__manifest__.py
odoo/addons/l10n_br_mdfe/hooks.py
odoo/addons/l10n_br_mdfe/constants/mdfe.py
odoo/addons/l10n_br_mdfe/constants/modal.py
odoo/addons/l10n_br_mdfe/data/ir_config_parameter.xml
odoo/addons/l10n_br_mdfe/demo/company_demo.xml
odoo/addons/l10n_br_mdfe/demo/fiscal_document_demo.xml
odoo/addons/l10n_br_mdfe/i18n/l10n_br_mdfe.pot
odoo/addons/l10n_br_mdfe/i18n/pt_BR.po
odoo/addons/l10n_br_mdfe/models/__init__.py
odoo/addons/l10n_br_mdfe/models/document.py
odoo/addons/l10n_br_mdfe/models/document_info.py
odoo/addons/l10n_br_mdfe/models/document_related.py
odoo/addons/l10n_br_mdfe/models/document_supplement.py
odoo/addons/l10n_br_mdfe/models/document_type.py
odoo/addons/l10n_br_mdfe/models/modal_aereo.py
odoo/addons/l10n_br_mdfe/models/modal_aquaviario.py
odoo/addons/l10n_br_mdfe/models/modal_ferroviario.py
odoo/addons/l10n_br_mdfe/models/modal_rodoviario.py
odoo/addons/l10n_br_mdfe/models/product_product.py
odoo/addons/l10n_br_mdfe/models/res_company.py
odoo/addons/l10n_br_mdfe/models/res_config_settings.py
odoo/addons/l10n_br_mdfe/models/res_partner.py
odoo/addons/l10n_br_mdfe/models/seguro_carga.py
odoo/addons/l10n_br_mdfe/models/transporte.py
odoo/addons/l10n_br_mdfe/readme/CONFIGURE.rst
odoo/addons/l10n_br_mdfe/readme/CONTRIBUTORS.rst
odoo/addons/l10n_br_mdfe/readme/DESCRIPTION.rst
odoo/addons/l10n_br_mdfe/readme/ROADMAP.rst
odoo/addons/l10n_br_mdfe/readme/USAGE.rst
odoo/addons/l10n_br_mdfe/report/__init__.py
odoo/addons/l10n_br_mdfe/report/damdfe_report.xml
odoo/addons/l10n_br_mdfe/report/ir_actions_report.py
odoo/addons/l10n_br_mdfe/security/ir.model.access.csv
odoo/addons/l10n_br_mdfe/static/description/icon.png
odoo/addons/l10n_br_mdfe/static/description/index.html
odoo/addons/l10n_br_mdfe/tests/__init__.py
odoo/addons/l10n_br_mdfe/tests/test_mdfe_damdfe.py
odoo/addons/l10n_br_mdfe/tests/test_mdfe_document.py
odoo14_addon_l10n_br_mdfe-14.0.1.9.0.dist-info/METADATA
odoo14_addon_l10n_br_mdfe-14.0.1.9.0.dist-info/WHEEL
odoo14_addon_l10n_br_mdfe-14.0.1.9.0.dist-info/top_level.txt
odoo14_addon_l10n_br_mdfe-14.0.1.9.0.dist-info/RECORD
